design.sv
// Code your design here
module sync_fifo(
  input clk,
  input reset,
  input wr_en,
  input rd_en,
  input [7:0] din,
  output reg [7:0] dout,
  output full,
  output empty
);
  reg [7:0] mem [0:7];
  reg [2:0] wr_ptr = 0;
  reg [2:0] rd_ptr = 0;
  reg [3:0] count = 0;
  assign full = (count == 8);
  assign empty = (count == 0);
  always @(posedge clk or posedge reset) begin
    if(reset) begin
      wr_ptr <= 0;
      rd_ptr <= 0;
      count <= 0;
      dout <= 0;
    end else begin
      if(wr_en && !full) begin
        mem[wr_ptr] <= din;
        wr_ptr <= wr_ptr+1;
        count <= count+1;
      end
      if(rd_en && !empty) begin
        dout <= mem[rd_ptr];
        rd_ptr <= rd_ptr+1;
        count <= count-1;
      end 
    end
  end
endmodule

testbench.sv
// Code your testbench here
// or browse Examples
module tb_sync_fifo;
  reg clk, reset, wr_en, rd_en;
  reg [7:0] din;
  wire [7:0] dout;
  wire full, empty;
  sync_fifo fifo_inst(
    .clk(clk),
    .reset(reset),
    .wr_en(wr_en),
    .rd_en(rd_en),
    .din(din),
    .dout(dout),
    .full(full),
    .empty(empty)
  );
  always #5 clk = ~clk;
    initial begin
      $monitor("Time = %0t | wr_en = %b | rd_en = %b | din = %h | dout = %h | full = %b | empty = %b", $time, wr_en, rd_en, din, dout, full, empty);
      $dumpfile("sync_fifo.vcd");
      $dumpvars;
      clk = 0;
      reset = 1; 
      wr_en = 0;
      rd_en = 0;
      din = 8'h00;
      #10 reset = 0;
      wr_en = 1;
      din = 8'hA1;
      din = 8'hB2; #10;
      din = 8'hC3; #10;
      wr_en = 0;
      rd_en = 1; #10;
      #10; rd_en = 0;
      wr_en = 1;
      din = 8'hE5; #10;
      wr_en = 0;
      rd_en = 1; #50;
      rd_en = 0;
      $finish;
    end 
endmodule

sync_fifo.vcd
$date
	Wed Jul  9 06:13:01 2025
$end
$version
	Icarus Verilog
$end
$timescale
	1s
$end
$scope module tb_sync_fifo $end
$var wire 1 ! full $end
$var wire 1 " empty $end
$var wire 8 # dout [7:0] $end
$var reg 1 $ clk $end
$var reg 8 % din [7:0] $end
$var reg 1 & rd_en $end
$var reg 1 ' reset $end
$var reg 1 ( wr_en $end
$scope module fifo_inst $end
$var wire 1 $ clk $end
$var wire 8 ) din [7:0] $end
$var wire 1 & rd_en $end
$var wire 1 ' reset $end
$var wire 1 ( wr_en $end
$var wire 1 ! full $end
$var wire 1 " empty $end
$var reg 4 * count [3:0] $end
$var reg 8 + dout [7:0] $end
$var reg 3 , rd_ptr [2:0] $end
$var reg 3 - wr_ptr [2:0] $end
$upscope $end
$upscope $end
$enddefinitions $end
$comment Show the parameter values. $end
$dumpall
$end
#0
$dumpvars
b0 -
b0 ,
b0 +
b0 *
b0 )
0(
1'
0&
b0 %
0$
b0 #
1"
0!
$end
#5
1$
#10
0$
b10110010 %
b10110010 )
1(
0'
#15
0"
b1 *
b1 -
1$
#20
0$
b11000011 %
b11000011 )
#25
b10 *
b10 -
1$
#30
0$
1&
0(
#35
b1 *
b1 ,
b10110010 #
b10110010 +
1$
#40
0$
#45
1"
b0 *
b10 ,
b11000011 #
b11000011 +
1$
#50
0$
b11100101 %
b11100101 )
1(
0&
#55
0"
b1 *
b11 -
1$
#60
0$
1&
0(
#65
1"
b0 *
b11 ,
b11100101 #
b11100101 +
1$
#70
0$
#75
1$
#80
0$
#85
1$
#90
0$
#95
1$
#100
0$
#105
1$
#110
0$
0&
